resimitpo/__init__.py
resimitpo/hessian.py
resimitpo/history.py
resimitpo/memory.py
resimitpo/resimitpo.py
resimitpo/step_finder.py
resimitpo/debug/__init__.py
resimitpo/debug/driver.py
resimitpo/debug/hessian.py
resimitpo/debug/history.py
resimitpo/debug/memory.py
resimitpo/debug/resimitpo.py
resimitpo/debug/step_finder.py
resimitpo-1.0.1.dist-info/licenses/LICENSE
resimitpo-1.0.1.dist-info/METADATA
resimitpo-1.0.1.dist-info/WHEEL
resimitpo-1.0.1.dist-info/top_level.txt
resimitpo-1.0.1.dist-info/RECORD
