Metadata-Version: 2.4
Name: resimitpo
Version: 1.0.1
Summary: Reverse communication nonlinear optimization solver for smooth unconstrained objectives
Home-page: https://gitlab.gwdg.de/nam/resimitpo/
Author: D.Russell Luke
Author-email: r.luke@math.uni-goettingen.de
Project-URL: Bug Tracker, https://gitlab.gwdg.de/nam/resimitpo/
Project-URL: repository, https://gitlab.gwdg.de/nam/resimitpo/
Classifier: Programming Language :: Python :: 3
Classifier: License :: OSI Approved :: GNU General Public License v3 (GPLv3)
Classifier: Operating System :: OS Independent
Requires-Python: >=3.6
License-File: LICENSE
Requires-Dist: numpy
Requires-Dist: matplotlib
Dynamic: license-file
